{"metadata": {"dbt_schema_version": "https://schemas.getdbt.com/dbt/run-results/v6.json", "dbt_version": "1.8.9", "generated_at": "2024-12-22T04:21:17.636537Z", "invocation_id": "e9cab55c-659a-4282-8b0b-43ac322d8e6a", "env": {}}, "results": [{"status": "success", "timing": [{"name": "compile", "started_at": "2024-12-22T04:21:17.349093Z", "completed_at": "2024-12-22T04:21:17.355287Z"}, {"name": "execute", "started_at": "2024-12-22T04:21:17.355770Z", "completed_at": "2024-12-22T04:21:17.458125Z"}], "thread_id": "Thread-1 (worker)", "execution_time": 0.11079239845275879, "adapter_response": {"_message": "CREATE VIEW", "code": "CREATE VIEW", "rows_affected": -1}, "message": "CREATE VIEW", "failures": null, "unique_id": "model.db_postgres.movies", "compiled": true, "compiled_code": "SELECT  CAST(id as INT) as movie_id, \n    TO_DATE(\"Release_Date\", 'YY-MM-DD') as release_date,\n    \"IMDB_URL\" as imdb_url,\n    CAST(CAST(\"Film_Noir\" as INT) as BOOLEAN) as film_noir\nFROM \"mlops\".\"source\".\"movies\"\n\n--     \"Film-Noir\",\n--     \"Action\",\n--     \"adventure\",\n--     \"horror\",\n--     \"war\",\n--     \"index\",\n--     \"romance\", \n--     \"Name\",\n--     \"western\",\n--     \"documentary\",\n--     \"Sci-Fi\",\n--     \"drama\",\n--     \"thriller\",\n--     \"crime\",\n--     \"Children's\",\n--     fantasy,\n--     animation,\n--     comedy,\n--     mystery, \n--     musical", "relation_name": "\"mlops\".\"target\".\"movies\""}, {"status": "success", "timing": [{"name": "compile", "started_at": "2024-12-22T04:21:17.465533Z", "completed_at": "2024-12-22T04:21:17.468711Z"}, {"name": "execute", "started_at": "2024-12-22T04:21:17.469228Z", "completed_at": "2024-12-22T04:21:17.510520Z"}], "thread_id": "Thread-1 (worker)", "execution_time": 0.04719710350036621, "adapter_response": {"_message": "CREATE VIEW", "code": "CREATE VIEW", "rows_affected": -1}, "message": "CREATE VIEW", "failures": null, "unique_id": "model.db_postgres.scores", "compiled": true, "compiled_code": "SELECT CAST(user_id as INT),\n    CAST(movie_id as INT),\n    CAST(rating as INT)\nFROM \"mlops\".\"source\".\"scores\"", "relation_name": "\"mlops\".\"target\".\"scores\""}, {"status": "success", "timing": [{"name": "compile", "started_at": "2024-12-22T04:21:17.515323Z", "completed_at": "2024-12-22T04:21:17.517900Z"}, {"name": "execute", "started_at": "2024-12-22T04:21:17.518400Z", "completed_at": "2024-12-22T04:21:17.563568Z"}], "thread_id": "Thread-1 (worker)", "execution_time": 0.050405025482177734, "adapter_response": {"_message": "CREATE VIEW", "code": "CREATE VIEW", "rows_affected": -1}, "message": "CREATE VIEW", "failures": null, "unique_id": "model.db_postgres.user", "compiled": true, "compiled_code": "SELECT CAST(id as INT) as user_id, \n    TO_TIMESTAMP(\"Active_Since\", 'YY-MM-DD HH24:MI:SS') at time zone 'utc' as active_since, \n    \"Occupation\"\nFROM \"mlops\".\"source\".\"users\"", "relation_name": "\"mlops\".\"target\".\"user\""}, {"status": "success", "timing": [{"name": "compile", "started_at": "2024-12-22T04:21:17.570569Z", "completed_at": "2024-12-22T04:21:17.573436Z"}, {"name": "execute", "started_at": "2024-12-22T04:21:17.573941Z", "completed_at": "2024-12-22T04:21:17.615281Z"}], "thread_id": "Thread-1 (worker)", "execution_time": 0.046270132064819336, "adapter_response": {"_message": "CREATE VIEW", "code": "CREATE VIEW", "rows_affected": -1}, "message": "CREATE VIEW", "failures": null, "unique_id": "model.db_postgres.scores_movies_users", "compiled": true, "compiled_code": "SELECT * FROM \"mlops\".\"target\".\"scores\" sc \nINNER JOIN \"mlops\".\"target\".\"movies\" using(movie_id)\nINNER JOIN \"mlops\".\"target\".\"user\" using(user_id)", "relation_name": "\"mlops\".\"target\".\"scores_movies_users\""}], "elapsed_time": 0.4344608783721924, "args": {"cache_selected_only": false, "show": false, "use_colors_file": true, "indirect_selection": "eager", "which": "build", "macro_debugging": false, "warn_error_options": {"include": [], "exclude": []}, "resource_types": [], "exclude": [], "include_saved_query": false, "strict_mode": false, "favor_state": false, "show_resource_report": false, "printer_width": 80, "enable_legacy_logger": false, "use_colors": true, "log_format": "json", "require_explicit_package_overrides_for_builtin_materializations": true, "static_parser": true, "defer": false, "write_json": true, "exclude_resource_types": [], "profiles_dir": "/home/gcartasso/.dbt", "export_saved_queries": false, "version_check": true, "print": true, "project_dir": "/home/gcartasso/Downloads/mlops-ecosystem-main/db_postgres", "log_path": "/home/gcartasso/Downloads/mlops-ecosystem-main/db_postgres/target/my_dbt_assets-bba41a5-ab59092", "log_format_file": "json", "empty": false, "source_freshness_run_project_hooks": false, "invocation_command": "dbt build --select fqn:*", "select": ["fqn:*"], "partial_parse_file_diff": true, "partial_parse": true, "quiet": false, "send_anonymous_usage_stats": false, "log_level_file": "debug", "vars": {}, "introspect": true, "log_level": "info", "target_path": "target/my_dbt_assets-bba41a5-ab59092", "require_resource_names_without_spaces": false, "populate_cache": true, "log_file_max_bytes": 10485760}}